cartesia/__init__.py
cartesia/api_status/__init__.py
cartesia/api_status/client.py
cartesia/api_status/requests/__init__.py
cartesia/api_status/requests/api_info.py
cartesia/api_status/types/__init__.py
cartesia/api_status/types/api_info.py
cartesia/auth/__init__.py
cartesia/auth/client.py
cartesia/auth/requests/__init__.py
cartesia/auth/requests/token_grant.py
cartesia/auth/requests/token_request.py
cartesia/auth/requests/token_response.py
cartesia/auth/types/__init__.py
cartesia/auth/types/token_grant.py
cartesia/auth/types/token_request.py
cartesia/auth/types/token_response.py
cartesia/base_client.py
cartesia/client.py
cartesia/core/__init__.py
cartesia/core/api_error.py
cartesia/core/client_wrapper.py
cartesia/core/datetime_utils.py
cartesia/core/file.py
cartesia/core/http_client.py
cartesia/core/jsonable_encoder.py
cartesia/core/pagination.py
cartesia/core/pydantic_utilities.py
cartesia/core/query_encoder.py
cartesia/core/remove_none_from_dict.py
cartesia/core/request_options.py
cartesia/core/serialization.py
cartesia/datasets/__init__.py
cartesia/datasets/requests/__init__.py
cartesia/datasets/requests/create_dataset_request.py
cartesia/datasets/requests/dataset.py
cartesia/datasets/requests/dataset_file.py
cartesia/datasets/requests/paginated_dataset_files.py
cartesia/datasets/requests/paginated_datasets.py
cartesia/datasets/types/__init__.py
cartesia/datasets/types/create_dataset_request.py
cartesia/datasets/types/dataset.py
cartesia/datasets/types/dataset_file.py
cartesia/datasets/types/file_purpose.py
cartesia/datasets/types/paginated_dataset_files.py
cartesia/datasets/types/paginated_datasets.py
cartesia/embedding/__init__.py
cartesia/embedding/types/__init__.py
cartesia/embedding/types/embedding.py
cartesia/environment.py
cartesia/infill/__init__.py
cartesia/infill/client.py
cartesia/py.typed
cartesia/stt/__init__.py
cartesia/stt/_async_websocket.py
cartesia/stt/_websocket.py
cartesia/stt/client.py
cartesia/stt/requests/__init__.py
cartesia-2.0.8.dist-info/LICENSE
cartesia-2.0.8.dist-info/METADATA
cartesia-2.0.8.dist-info/WHEEL
cartesia-2.0.8.dist-info/RECORD
