Metadata-Version: 2.1
Name: cartesia
Version: 2.0.8
Summary: 
Requires-Python: >=3.8,<4.0
Classifier: Intended Audience :: Developers
Classifier: Operating System :: MacOS
Classifier: Operating System :: Microsoft :: Windows
Classifier: Operating System :: OS Independent
Classifier: Operating System :: POSIX
Classifier: Operating System :: POSIX :: Linux
Classifier: Programming Language :: Python
Classifier: Programming Language :: Python :: 3
Classifier: Programming Language :: Python :: 3.8
Classifier: Programming Language :: Python :: 3.9
Classifier: Programming Language :: Python :: 3.10
Classifier: Programming Language :: Python :: 3.11
Classifier: Programming Language :: Python :: 3.12
Classifier: Topic :: Software Development :: Libraries :: Python Modules
Classifier: Typing :: Typed
Requires-Dist: aiohttp (>=3.10.10)
Requires-Dist: audioop-lts (==0.2.1) ; python_version >= "3.13" and python_version < "4.0"
Requires-Dist: httpx (>=0.21.2)
Requires-Dist: httpx-sse (==0.4.0)
Requires-Dist: iterators (>=0.2.0)
Requires-Dist: pydantic (>=1.9.2)
Requires-Dist: pydantic-core (>=2.18.2,<3.0.0)
Requires-Dist: pydub (>=0.25.1)
Requires-Dist: typing_extensions (>=4.0.0)
Requires-Dist: websockets (>=10.4)
